package com.achijones.profootballcoach;

import android.os.AsyncTask;

class Home$GetRosterFileTask
  extends AsyncTask<String, Void, String>
{
  Home$GetRosterFileTask(Home paramHome) {}
  
  /* Error */
  protected String doInBackground(String[] paramArrayOfString)
  {
    // Byte code:
    //   0: new 35	java/io/PrintWriter
    //   3: dup
    //   4: aload_0
    //   5: getfield 14	com/achijones/profootballcoach/Home$GetRosterFileTask:this$0	Lcom/achijones/profootballcoach/Home;
    //   8: getfield 39	com/achijones/profootballcoach/Home:rosterFile	Ljava/io/File;
    //   11: invokespecial 42	java/io/PrintWriter:<init>	(Ljava/io/File;)V
    //   14: astore_3
    //   15: aload_3
    //   16: ldc 44
    //   18: invokevirtual 48	java/io/PrintWriter:print	(Ljava/lang/String;)V
    //   21: aload_3
    //   22: invokevirtual 51	java/io/PrintWriter:close	()V
    //   25: new 53	java/io/FileWriter
    //   28: dup
    //   29: aload_0
    //   30: getfield 14	com/achijones/profootballcoach/Home$GetRosterFileTask:this$0	Lcom/achijones/profootballcoach/Home;
    //   33: getfield 39	com/achijones/profootballcoach/Home:rosterFile	Ljava/io/File;
    //   36: iconst_1
    //   37: invokespecial 56	java/io/FileWriter:<init>	(Ljava/io/File;Z)V
    //   40: astore 4
    //   42: new 58	java/io/BufferedWriter
    //   45: dup
    //   46: aload 4
    //   48: invokespecial 61	java/io/BufferedWriter:<init>	(Ljava/io/Writer;)V
    //   51: astore 5
    //   53: new 35	java/io/PrintWriter
    //   56: dup
    //   57: aload 5
    //   59: invokespecial 62	java/io/PrintWriter:<init>	(Ljava/io/Writer;)V
    //   62: astore 6
    //   64: aconst_null
    //   65: astore_3
    //   66: new 64	java/net/URL
    //   69: dup
    //   70: aload_1
    //   71: iconst_0
    //   72: aaload
    //   73: invokespecial 66	java/net/URL:<init>	(Ljava/lang/String;)V
    //   76: invokevirtual 70	java/net/URL:openConnection	()Ljava/net/URLConnection;
    //   79: invokevirtual 76	java/net/URLConnection:getInputStream	()Ljava/io/InputStream;
    //   82: astore_1
    //   83: aload_1
    //   84: invokevirtual 82	java/io/InputStream:read	()I
    //   87: istore_2
    //   88: iload_2
    //   89: iconst_m1
    //   90: if_icmpeq +42 -> 132
    //   93: aload 6
    //   95: iload_2
    //   96: i2c
    //   97: invokevirtual 85	java/io/PrintWriter:print	(C)V
    //   100: goto -17 -> 83
    //   103: astore_1
    //   104: getstatic 91	java/lang/System:out	Ljava/io/PrintStream;
    //   107: new 93	java/lang/StringBuilder
    //   110: dup
    //   111: invokespecial 94	java/lang/StringBuilder:<init>	()V
    //   114: ldc 96
    //   116: invokevirtual 100	java/lang/StringBuilder:append	(Ljava/lang/String;)Ljava/lang/StringBuilder;
    //   119: aload_1
    //   120: invokevirtual 104	java/net/MalformedURLException:toString	()Ljava/lang/String;
    //   123: invokevirtual 100	java/lang/StringBuilder:append	(Ljava/lang/String;)Ljava/lang/StringBuilder;
    //   126: invokevirtual 105	java/lang/StringBuilder:toString	()Ljava/lang/String;
    //   129: invokevirtual 110	java/io/PrintStream:println	(Ljava/lang/String;)V
    //   132: aload 6
    //   134: ifnull +12 -> 146
    //   137: iconst_0
    //   138: ifeq +168 -> 306
    //   141: aload 6
    //   143: invokevirtual 51	java/io/PrintWriter:close	()V
    //   146: aload 5
    //   148: ifnull +12 -> 160
    //   151: iconst_0
    //   152: ifeq +190 -> 342
    //   155: aload 5
    //   157: invokevirtual 111	java/io/BufferedWriter:close	()V
    //   160: aload 4
    //   162: ifnull +12 -> 174
    //   165: iconst_0
    //   166: ifeq +212 -> 378
    //   169: aload 4
    //   171: invokevirtual 112	java/io/FileWriter:close	()V
    //   174: ldc 114
    //   176: areturn
    //   177: astore_3
    //   178: getstatic 91	java/lang/System:out	Ljava/io/PrintStream;
    //   181: aload_3
    //   182: invokevirtual 115	java/lang/Exception:toString	()Ljava/lang/String;
    //   185: invokevirtual 110	java/io/PrintStream:println	(Ljava/lang/String;)V
    //   188: goto -163 -> 25
    //   191: astore_1
    //   192: getstatic 91	java/lang/System:out	Ljava/io/PrintStream;
    //   195: new 93	java/lang/StringBuilder
    //   198: dup
    //   199: invokespecial 94	java/lang/StringBuilder:<init>	()V
    //   202: ldc 117
    //   204: invokevirtual 100	java/lang/StringBuilder:append	(Ljava/lang/String;)Ljava/lang/StringBuilder;
    //   207: aload_1
    //   208: invokevirtual 118	java/io/IOException:toString	()Ljava/lang/String;
    //   211: invokevirtual 100	java/lang/StringBuilder:append	(Ljava/lang/String;)Ljava/lang/StringBuilder;
    //   214: invokevirtual 105	java/lang/StringBuilder:toString	()Ljava/lang/String;
    //   217: invokevirtual 110	java/io/PrintStream:println	(Ljava/lang/String;)V
    //   220: goto -88 -> 132
    //   223: astore_3
    //   224: aload_3
    //   225: athrow
    //   226: astore_1
    //   227: aload 6
    //   229: ifnull +12 -> 241
    //   232: aload_3
    //   233: ifnull +92 -> 325
    //   236: aload 6
    //   238: invokevirtual 51	java/io/PrintWriter:close	()V
    //   241: aload_1
    //   242: athrow
    //   243: astore_3
    //   244: aload_3
    //   245: athrow
    //   246: astore_1
    //   247: aload 5
    //   249: ifnull +12 -> 261
    //   252: aload_3
    //   253: ifnull +108 -> 361
    //   256: aload 5
    //   258: invokevirtual 111	java/io/BufferedWriter:close	()V
    //   261: aload_1
    //   262: athrow
    //   263: astore_3
    //   264: aload_3
    //   265: athrow
    //   266: astore_1
    //   267: aload 4
    //   269: ifnull +12 -> 281
    //   272: aload_3
    //   273: ifnull +124 -> 397
    //   276: aload 4
    //   278: invokevirtual 112	java/io/FileWriter:close	()V
    //   281: aload_1
    //   282: athrow
    //   283: astore_1
    //   284: getstatic 91	java/lang/System:out	Ljava/io/PrintStream;
    //   287: aload_1
    //   288: invokevirtual 118	java/io/IOException:toString	()Ljava/lang/String;
    //   291: invokevirtual 110	java/io/PrintStream:println	(Ljava/lang/String;)V
    //   294: goto -120 -> 174
    //   297: astore_1
    //   298: new 120	java/lang/NullPointerException
    //   301: dup
    //   302: invokespecial 121	java/lang/NullPointerException:<init>	()V
    //   305: athrow
    //   306: aload 6
    //   308: invokevirtual 51	java/io/PrintWriter:close	()V
    //   311: goto -165 -> 146
    //   314: astore 6
    //   316: aload_3
    //   317: aload 6
    //   319: invokevirtual 125	java/lang/Throwable:addSuppressed	(Ljava/lang/Throwable;)V
    //   322: goto -81 -> 241
    //   325: aload 6
    //   327: invokevirtual 51	java/io/PrintWriter:close	()V
    //   330: goto -89 -> 241
    //   333: astore_1
    //   334: new 120	java/lang/NullPointerException
    //   337: dup
    //   338: invokespecial 121	java/lang/NullPointerException:<init>	()V
    //   341: athrow
    //   342: aload 5
    //   344: invokevirtual 111	java/io/BufferedWriter:close	()V
    //   347: goto -187 -> 160
    //   350: astore 5
    //   352: aload_3
    //   353: aload 5
    //   355: invokevirtual 125	java/lang/Throwable:addSuppressed	(Ljava/lang/Throwable;)V
    //   358: goto -97 -> 261
    //   361: aload 5
    //   363: invokevirtual 111	java/io/BufferedWriter:close	()V
    //   366: goto -105 -> 261
    //   369: astore_1
    //   370: new 120	java/lang/NullPointerException
    //   373: dup
    //   374: invokespecial 121	java/lang/NullPointerException:<init>	()V
    //   377: athrow
    //   378: aload 4
    //   380: invokevirtual 112	java/io/FileWriter:close	()V
    //   383: goto -209 -> 174
    //   386: astore 4
    //   388: aload_3
    //   389: aload 4
    //   391: invokevirtual 125	java/lang/Throwable:addSuppressed	(Ljava/lang/Throwable;)V
    //   394: goto -113 -> 281
    //   397: aload 4
    //   399: invokevirtual 112	java/io/FileWriter:close	()V
    //   402: goto -121 -> 281
    //   405: astore_1
    //   406: goto -179 -> 227
    //   409: astore_1
    //   410: aconst_null
    //   411: astore_3
    //   412: goto -165 -> 247
    //   415: astore_1
    //   416: aconst_null
    //   417: astore_3
    //   418: goto -151 -> 267
    // Local variable table:
    //   start	length	slot	name	signature
    //   0	421	0	this	GetRosterFileTask
    //   0	421	1	paramArrayOfString	String[]
    //   87	9	2	i	int
    //   14	52	3	localPrintWriter1	java.io.PrintWriter
    //   177	5	3	localException	Exception
    //   223	10	3	localThrowable1	Throwable
    //   243	10	3	localThrowable2	Throwable
    //   263	126	3	localThrowable3	Throwable
    //   411	7	3	localObject	Object
    //   40	339	4	localFileWriter	java.io.FileWriter
    //   386	12	4	localThrowable4	Throwable
    //   51	292	5	localBufferedWriter	java.io.BufferedWriter
    //   350	12	5	localThrowable5	Throwable
    //   62	245	6	localPrintWriter2	java.io.PrintWriter
    //   314	12	6	localThrowable6	Throwable
    // Exception table:
    //   from	to	target	type
    //   66	83	103	java/net/MalformedURLException
    //   83	88	103	java/net/MalformedURLException
    //   93	100	103	java/net/MalformedURLException
    //   0	25	177	java/lang/Exception
    //   66	83	191	java/io/IOException
    //   83	88	191	java/io/IOException
    //   93	100	191	java/io/IOException
    //   66	83	223	java/lang/Throwable
    //   83	88	223	java/lang/Throwable
    //   93	100	223	java/lang/Throwable
    //   104	132	223	java/lang/Throwable
    //   192	220	223	java/lang/Throwable
    //   224	226	226	finally
    //   53	64	243	java/lang/Throwable
    //   241	243	243	java/lang/Throwable
    //   298	306	243	java/lang/Throwable
    //   306	311	243	java/lang/Throwable
    //   316	322	243	java/lang/Throwable
    //   325	330	243	java/lang/Throwable
    //   244	246	246	finally
    //   42	53	263	java/lang/Throwable
    //   261	263	263	java/lang/Throwable
    //   334	342	263	java/lang/Throwable
    //   342	347	263	java/lang/Throwable
    //   352	358	263	java/lang/Throwable
    //   361	366	263	java/lang/Throwable
    //   264	266	266	finally
    //   25	42	283	java/io/IOException
    //   169	174	283	java/io/IOException
    //   276	281	283	java/io/IOException
    //   281	283	283	java/io/IOException
    //   370	378	283	java/io/IOException
    //   378	383	283	java/io/IOException
    //   388	394	283	java/io/IOException
    //   397	402	283	java/io/IOException
    //   141	146	297	java/lang/Throwable
    //   236	241	314	java/lang/Throwable
    //   155	160	333	java/lang/Throwable
    //   256	261	350	java/lang/Throwable
    //   169	174	369	java/lang/Throwable
    //   276	281	386	java/lang/Throwable
    //   66	83	405	finally
    //   83	88	405	finally
    //   93	100	405	finally
    //   104	132	405	finally
    //   192	220	405	finally
    //   53	64	409	finally
    //   141	146	409	finally
    //   236	241	409	finally
    //   241	243	409	finally
    //   298	306	409	finally
    //   306	311	409	finally
    //   316	322	409	finally
    //   325	330	409	finally
    //   42	53	415	finally
    //   155	160	415	finally
    //   256	261	415	finally
    //   261	263	415	finally
    //   334	342	415	finally
    //   342	347	415	finally
    //   352	358	415	finally
    //   361	366	415	finally
  }
  
  protected void onPostExecute(String paramString)
  {
    this$0.newLeagueRosterFile();
  }
}

/* Location:
 * Qualified Name:     com.achijones.profootballcoach.Home.GetRosterFileTask
 * Java Class Version: 6 (50.0)
 * JD-Core Version:    0.7.1
 */